kbastroutils/__init__.py
kbastroutils/container.py
kbastroutils/dqmask.py
kbastroutils/gnd.py
kbastroutils/grismapcorr.py
kbastroutils/grismcalibpath.py
kbastroutils/grismconf.py
kbastroutils/grismcrclean.py
kbastroutils/grismdrz.py
kbastroutils/grismmeta.py
kbastroutils/grismmodel.py
kbastroutils/grismsens.py
kbastroutils/mag2flux.py
kbastroutils/make_sip.py
kbastroutils/photapcorr.py
kbastroutils/segmentation.py
kbastroutils/sub2full.py
kbastroutils-2.6.2.dist-info/LICENSE
kbastroutils-2.6.2.dist-info/METADATA
kbastroutils-2.6.2.dist-info/WHEEL
kbastroutils-2.6.2.dist-info/top_level.txt
kbastroutils-2.6.2.dist-info/RECORD
